akara/__init__.py
akara/dictionary.py
akara/edit_distance.py
akara/node.py
akara/spell_checker.py
akara_python-1.0.0.dist-info/METADATA
akara_python-1.0.0.dist-info/WHEEL
akara_python-1.0.0.dist-info/top_level.txt
akara_python-1.0.0.dist-info/RECORD
